linguist_breakdown/__init__.py
linguist_breakdown/breakdown.py
test/__init__.py
test/unit/__init__.py
test/unit/test_linguist.py
linguist_breakdown-2.0.0.dist-info/LICENSE
linguist_breakdown-2.0.0.dist-info/METADATA
linguist_breakdown-2.0.0.dist-info/WHEEL
linguist_breakdown-2.0.0.dist-info/entry_points.txt
linguist_breakdown-2.0.0.dist-info/top_level.txt
linguist_breakdown-2.0.0.dist-info/RECORD
