Metadata-Version: 2.1
Name: linguist-breakdown
Version: 2.0.0
Summary: View the language breakdown of your entire GitHub account.
Home-page: http://github.com/justintime50/linguist-breakdown
Author: Justintime50
License: MIT
Platform: UNKNOWN
Classifier: Programming Language :: Python :: 3
Classifier: License :: OSI Approved :: MIT License
Classifier: Operating System :: OS Independent
Requires-Python: >=3.6
Requires-Dist: matplotlib (>=3.2.0)
Requires-Dist: PyGithub (>=1.51)
Provides-Extra: dev
Requires-Dist: pytest (>=6.0.0) ; extra == 'dev'
Requires-Dist: pytest-cov (>=2.10.0) ; extra == 'dev'
Requires-Dist: coveralls (>=2.1.2) ; extra == 'dev'
Requires-Dist: flake8 (>=3.8.0) ; extra == 'dev'
Requires-Dist: mock (>=4.0.0) ; extra == 'dev'
